repoproviders/__init__.py
repoproviders/__main__.py
repoproviders/_version.py
repoproviders/py.typed
repoproviders/utils.py
repoproviders/fetchers/__init__.py
repoproviders/fetchers/base.py
repoproviders/fetchers/dataverse.py
repoproviders/fetchers/fetcher.py
repoproviders/fetchers/git.py
repoproviders/resolvers/__init__.py
repoproviders/resolvers/base.py
repoproviders/resolvers/dataverse.json
repoproviders/resolvers/doi.py
repoproviders/resolvers/feature_detect.py
repoproviders/resolvers/git.py
repoproviders/resolvers/repos.py
repoproviders/resolvers/resolver.py
repoproviders/resolvers/serialize.py
repoproviders/resolvers/wellknown.py
repoproviders-0.1.2.dist-info/METADATA
repoproviders-0.1.2.dist-info/WHEEL
repoproviders-0.1.2.dist-info/entry_points.txt
repoproviders-0.1.2.dist-info/licenses/LICENSE
repoproviders-0.1.2.dist-info/RECORD
