Metadata-Version: 2.4
Name: repoproviders
Version: 0.1.2
Summary: Detect, resolve and fetch repositories of content
Project-URL: Homepage, https://github.com/yuvipanda/repoproviders
Project-URL: Source Code, https://github.com/yuvipanda/repoproviders
Project-URL: Bug Tracker, https://github.com/yuvipanda/repoproviders/issues
Project-URL: Documentation, https://repoproviders.readthedocs.io
Project-URL: Download, https://pypi.org/project/repoproviders/#files
Author-email: Yuvi Panda <yuvipanda@gmail.com>
License-Expression: BSD-3-Clause
License-File: LICENSE
Classifier: Development Status :: 2 - Pre-Alpha
Classifier: Intended Audience :: Science/Research
Classifier: License :: OSI Approved :: BSD License
Classifier: Operating System :: OS Independent
Classifier: Programming Language :: Python :: 3 :: Only
Classifier: Typing :: Typed
Requires-Dist: aiohttp
Requires-Dist: yarl
Provides-Extra: dev
Requires-Dist: hatch; extra == 'dev'
Requires-Dist: pre-commit; extra == 'dev'
